cblack.py
cblack-22.3.0.dist-info/LICENSE
cblack-22.3.0.dist-info/METADATA
cblack-22.3.0.dist-info/WHEEL
cblack-22.3.0.dist-info/entry_points.txt
cblack-22.3.0.dist-info/top_level.txt
cblack-22.3.0.dist-info/RECORD
